mcrentcast/__init__.py
mcrentcast/config.py
mcrentcast/database.py
mcrentcast/mock_api.py
mcrentcast/models.py
mcrentcast/rentcast_client.py
mcrentcast/server.py
mcrentcast-0.1.0.dist-info/METADATA
mcrentcast-0.1.0.dist-info/WHEEL
mcrentcast-0.1.0.dist-info/entry_points.txt
mcrentcast-0.1.0.dist-info/RECORD
