Metadata-Version: 2.4
Name: mcrentcast
Version: 0.1.0
Summary: MCP Server for Rentcast API with intelligent caching and rate limiting
Project-URL: Homepage, https://git.supported.systems/MCP/mcrentcast
Project-URL: Repository, https://git.supported.systems/MCP/mcrentcast.git
Project-URL: Documentation, https://git.supported.systems/MCP/mcrentcast#readme
Author-email: Ryan Malloy <ryan@supported.systems>
License: MIT
Classifier: Development Status :: 4 - Beta
Classifier: Intended Audience :: Developers
Classifier: License :: OSI Approved :: MIT License
Classifier: Programming Language :: Python :: 3
Classifier: Programming Language :: Python :: 3.13
Requires-Python: >=3.13
Requires-Dist: aiofiles>=24.1.0
Requires-Dist: fastapi>=0.116.1
Requires-Dist: fastmcp>=2.12.2
Requires-Dist: httpx>=0.27.0
Requires-Dist: pydantic>=2.11.7
Requires-Dist: python-dotenv>=1.0.0
Requires-Dist: sqlalchemy>=2.0.43
Requires-Dist: structlog>=24.4.0
Requires-Dist: tenacity>=8.2.3
Requires-Dist: typing-extensions>=4.12.0
Requires-Dist: uvicorn>=0.35.0
